Metadata-Version: 1.1
Name: negotiator-3k
Version: 1.0.0
Summary: 
